odoo8_addon_mgmtsystem_health_safety-8.0.1.0.0.99.dev3-py2.7-nspkg.pth
odoo8_addon_mgmtsystem_health_safety-8.0.1.0.0.99.dev3.dist-info/DESCRIPTION.rst
odoo8_addon_mgmtsystem_health_safety-8.0.1.0.0.99.dev3.dist-info/METADATA
odoo8_addon_mgmtsystem_health_safety-8.0.1.0.0.99.dev3.dist-info/RECORD
odoo8_addon_mgmtsystem_health_safety-8.0.1.0.0.99.dev3.dist-info/WHEEL
odoo8_addon_mgmtsystem_health_safety-8.0.1.0.0.99.dev3.dist-info/metadata.json
odoo8_addon_mgmtsystem_health_safety-8.0.1.0.0.99.dev3.dist-info/namespace_packages.txt
odoo8_addon_mgmtsystem_health_safety-8.0.1.0.0.99.dev3.dist-info/top_level.txt
odoo_addons/mgmtsystem_health_safety/README.rst
odoo_addons/mgmtsystem_health_safety/__init__.py
odoo_addons/mgmtsystem_health_safety/__openerp__.py
odoo_addons/mgmtsystem_health_safety/data/mgmtsystem_system.xml
odoo_addons/mgmtsystem_health_safety/i18n/de.po
odoo_addons/mgmtsystem_health_safety/i18n/fr.po
odoo_addons/mgmtsystem_health_safety/i18n/mgmtsystem_health_safety.pot
odoo_addons/mgmtsystem_health_safety/i18n/nb.po
odoo_addons/mgmtsystem_health_safety/i18n/pt_BR.po
odoo_addons/mgmtsystem_health_safety/i18n/sv.po
odoo_addons/mgmtsystem_health_safety/i18n/vi.po
odoo_addons/mgmtsystem_health_safety/static/description/icon.png
