Metadata-Version: 2.0
Name: odoo8-addon-mgmtsystem-health-safety
Version: 8.0.1.0.0.99.dev3
Summary: Health and Safety Management System
Home-page: http://www.savoirfairelinux.com
Author: Savoir-faire Linux, Odoo Community Association (OCA)
Author-email: support@odoo-community.org
License: AGPL-3
Platform: UNKNOWN
Classifier: Programming Language :: Python
Classifier: Framework :: Odoo
Classifier: License :: OSI Approved :: GNU Affero General Public License v3
Requires-Python: ~=2.7
Requires-Dist: odoo (<9.0a,>=8.0a)
Requires-Dist: odoo8-addon-document-page-health-safety-manual
Requires-Dist: odoo8-addon-mgmtsystem-audit
Requires-Dist: odoo8-addon-mgmtsystem-claim
Requires-Dist: odoo8-addon-mgmtsystem-hazard
Requires-Dist: odoo8-addon-mgmtsystem-review
